{
	"configurations" : 
	[
		{
			"directories" : 
			[
				{
					"build" : ".",
					"jsonFile" : "directory-.-Release-d0094a50bb2071803777.json",
					"minimumCMakeVersion" : 
					{
						"string" : "3.21"
					},
					"projectIndex" : 0,
					"source" : ".",
					"targetIndexes" : 
					[
						0
					]
				}
			],
			"name" : "Release",
			"projects" : 
			[
				{
					"directoryIndexes" : 
					[
						0
					],
					"name" : "PEA",
					"targetIndexes" : 
					[
						0
					]
				}
			],
			"targets" : 
			[
				{
					"directoryIndex" : 0,
					"id" : "PEA_PROJ2::@6890427a1f51a3e7e1df",
					"jsonFile" : "target-PEA_PROJ2-Release-f441072640e5658634c3.json",
					"name" : "PEA_PROJ2",
					"projectIndex" : 0
				}
			]
		}
	],
	"kind" : "codemodel",
	"paths" : 
	{
		"build" : "C:/Users/fizyk/CLionProjects/PEA_PROJ2/cmake-build-release",
		"source" : "C:/Users/fizyk/CLionProjects/PEA_PROJ2"
	},
	"version" : 
	{
		"major" : 2,
		"minor" : 3
	}
}
